{"connection-pools":{"db-3-mysql-gcp_api_34_31_backup_1697428211":{"numConnections":1,"numIdleConnections":1,"numBusyConnections":0,"minPoolSize":1,"maxPoolSize":15,"numThreadsAwaitingCheckoutDefaultUser":0},"db-5-mysql-gcp_api_1866_2":{"numConnections":2,"numIdleConnections":1,"numBusyConnections":1,"minPoolSize":1,"maxPoolSize":15,"numThreadsAwaitingCheckoutDefaultUser":0},"db-4-mysql-gcp_api_556":{"numConnections":15,"numIdleConnections":15,"numBusyConnections":0,"minPoolSize":1,"maxPoolSize":15,"numThreadsAwaitingCheckoutDefaultUser":0},"db-2-mysql-gcp_api_6":{"numConnections":1,"numIdleConnections":1,"numBusyConnections":0,"minPoolSize":1,"maxPoolSize":15,"numThreadsAwaitingCheckoutDefaultUser":0},"metabase-mysql-app-db":{"numConnections":15,"numIdleConnections":14,"numBusyConnections":1,"minPoolSize":1,"maxPoolSize":15,"numThreadsAwaitingCheckoutDefaultUser":0}}}